relionai/__init__.py
relionai/aws_logging_handlers/__init__.c
relionai/aws_logging_handlers/__init__.cpython-38-darwin.so
relionai/aws_logging_handlers/__init__.py
relionai/aws_logging_handlers/Kinesis/__init__.py
relionai/aws_logging_handlers/S3/__init__.py
relionai/aws_logging_handlers/tasks/__init__.py
relionai/aws_logging_handlers/validation/__init__.py
relionai/recommendation_systems/__init__.py
relionai/recommendation_systems/evaluation.c
relionai/recommendation_systems/evaluation.cpython-38-darwin.so
relionai/recommendation_systems/evaluation.py
relionai/recommendation_systems/monitoring.c
relionai/recommendation_systems/monitoring.cpython-38-darwin.so
relionai/recommendation_systems/monitoring.py
relionai/recommendation_systems/timeseries_splits.c
relionai/recommendation_systems/timeseries_splits.cpython-38-darwin.so
relionai/recommendation_systems/timeseries_splits.py
relionai/tabular_classification/__init__.py
relionai/tabular_classification/evaluation.c
relionai/tabular_classification/evaluation.cpython-38-darwin.so
relionai/tabular_classification/evaluation.py
relionai/tabular_classification/monitoring.c
relionai/tabular_classification/monitoring.cpython-38-darwin.so
relionai/tabular_classification/monitoring.py
relionai/tabular_classification/tabular_data_tests.c
relionai/tabular_classification/tabular_data_tests.cpython-38-darwin.so
relionai/tabular_classification/tabular_data_tests.py
relionai/timeseries_regression/__init__.py
relionai/timeseries_regression/evaluation.c
relionai/timeseries_regression/evaluation.cpython-38-darwin.so
relionai/timeseries_regression/evaluation.py
relionai/timeseries_regression/monitoring.c
relionai/timeseries_regression/monitoring.cpython-38-darwin.so
relionai/timeseries_regression/monitoring.py
relionai/timeseries_regression/timeseries_splits.c
relionai/timeseries_regression/timeseries_splits.cpython-38-darwin.so
relionai/timeseries_regression/timeseries_splits.py
relionai-0.0.1a0.dist-info/AUTHORS.rst
relionai-0.0.1a0.dist-info/METADATA
relionai-0.0.1a0.dist-info/WHEEL
relionai-0.0.1a0.dist-info/top_level.txt
relionai-0.0.1a0.dist-info/RECORD
