Metadata-Version: 2.1
Name: relionai
Version: 0.0.1a0
Summary: Comprehensive ML Testing directly into your stack with just a few lines of code
Home-page: https://github.com/mo-messidi/relionai
Author: Mo Messidi
Author-email: messidi.mo@gmail.com
License: UNKNOWN
Keywords: relionai
Platform: UNKNOWN
Classifier: Development Status :: 2 - Pre-Alpha
Classifier: Intended Audience :: Developers
Classifier: Natural Language :: English
Classifier: Programming Language :: Python :: 3
Classifier: Programming Language :: Python :: 3.6
Classifier: Programming Language :: Python :: 3.7
Classifier: Programming Language :: Python :: 3.8
Requires-Python: >=3.6
License-File: AUTHORS.rst
Requires-Dist: pandas
Requires-Dist: numpy
Requires-Dist: cython
Requires-Dist: scikit-learn
Requires-Dist: matplotlib
Requires-Dist: seaborn
Requires-Dist: dataclasses
Requires-Dist: shap
Requires-Dist: sdv
Requires-Dist: mlxtend
Requires-Dist: boto3
Requires-Dist: imblearn
Requires-Dist: emoji
Requires-Dist: llvmlite (==0.38.0)
Requires-Dist: matplotlib (==3.5.1)
Requires-Dist: mlxtend (==0.19.0)
Requires-Dist: numba (==0.55.1)
Requires-Dist: numpy (==1.21.5)
Requires-Dist: packaging (==21.3)
Requires-Dist: pandas (==1.3.5)
Requires-Dist: pillow (==9.0.1)
Requires-Dist: psutil (==5.9.0)
Requires-Dist: pyparsing (==3.0.7)
Requires-Dist: python-dateutil (==2.8.2)
Requires-Dist: pyts (==0.12.0)
Requires-Dist: pytz (==2021.3)
Requires-Dist: pyyaml (==5.4.1)
Requires-Dist: rdt (==0.6.3)
Requires-Dist: s3transfer (==0.5.1)
Requires-Dist: scikit-learn (==1.0.2)
Requires-Dist: scipy (==1.7.3)
Requires-Dist: sdmetrics (==0.4.1)
Requires-Dist: sdv (==0.13.1)
Requires-Dist: seaborn (==0.11.2)
Requires-Dist: shap (==0.40.0)
Requires-Dist: six (==1.16.0)
Requires-Dist: slicer (==0.0.7)
Requires-Dist: text-unidecode (==1.3)
Requires-Dist: threadpoolctl (==3.1.0)
Requires-Dist: torch (==1.10.2)
Requires-Dist: torchvision (==0.11.3)
Requires-Dist: tqdm (==4.62.3)
Requires-Dist: typing-extensions (==4.1.1)
Requires-Dist: urllib3 (==1.26.8)
Requires-Dist: setuptools (==60.9.3)
